sieve/__init__.py
sieve/_cli/__init__.py
sieve/_cli/sieve.py
sieve/_cli/commands/__init__.py
sieve/_cli/commands/secret.py
sieve/_openapi/__init__.py
sieve/_openapi/api_client.py
sieve/_openapi/api_response.py
sieve/_openapi/configuration.py
sieve/_openapi/exceptions.py
sieve/_openapi/rest.py
sieve/_openapi/api/__init__.py
sieve/_openapi/api/default_api.py
sieve/_openapi/models/__init__.py
sieve/_openapi/models/body_get_upload_url_v1_upload_url_post.py
sieve/_openapi/models/compact_function_app.py
sieve/_openapi/models/config_model.py
sieve/_openapi/models/detailed_usage.py
sieve/_openapi/models/directory_response.py
sieve/_openapi/models/edit_function_request.py
sieve/_openapi/models/edit_function_version_request.py
sieve/_openapi/models/end_time.py
sieve/_openapi/models/end_timestamp.py
sieve/_openapi/models/environment_variable.py
sieve/_openapi/models/function.py
sieve/_openapi/models/function_app.py
sieve/_openapi/models/http_validation_error.py
sieve/_openapi/models/id_response.py
sieve/_openapi/models/input_output.py
sieve/_openapi/models/inputs.py
sieve/_openapi/models/job.py
sieve/_openapi/models/job_cost_response.py
sieve/_openapi/models/job_outputs_inner.py
sieve/_openapi/models/job_response.py
sieve/_openapi/models/job_without_output_response.py
sieve/_openapi/models/list_function_jobs_response.py
sieve/_openapi/models/list_response_job.py
sieve/_openapi/models/list_response_secret.py
sieve/_openapi/models/location_inner.py
sieve/_openapi/models/log.py
sieve/_openapi/models/logs_data.py
sieve/_openapi/models/logs_label.py
sieve/_openapi/models/logs_response.py
sieve/_openapi/models/machine_type_usage.py
sieve/_openapi/models/new_output_response.py
sieve/_openapi/models/onboarding_request.py
sieve/_openapi/models/organization_model.py
sieve/_openapi/models/outputs_inner.py
sieve/_openapi/models/push_request.py
sieve/_openapi/models/push_response.py
sieve/_openapi/models/restart.py
sieve/_openapi/models/secret.py
sieve/_openapi/models/start_time.py
sievedata-1.5.0.dist-info/LICENSE.md
sievedata-1.5.0.dist-info/METADATA
sievedata-1.5.0.dist-info/WHEEL
sievedata-1.5.0.dist-info/entry_points.txt
sievedata-1.5.0.dist-info/top_level.txt
sievedata-1.5.0.dist-info/RECORD
